fsrpn/__init__.py
fsrpn-0.0.0.dist-info/METADATA
fsrpn-0.0.0.dist-info/WHEEL
fsrpn-0.0.0.dist-info/licenses/LICENCE
fsrpn-0.0.0.dist-info/RECORD
