Metadata-Version: 2.1
Name: fsrpn
Version: 0.0.0
Summary: A Python implemented Lexer and Parser (and simple Interpreter) for Microsoft Flight Simulator Reverse Polish Notation ("XML-Programming")
Project-URL: Homepage, https://bitbucket.org/kleinjakob/fsrpn/
Project-URL: Bug Tracker, https://bitbucket.org/kleinjakob/fsrpn/issues
Author-email: Jakob Klein <mail@kleinjakob.at>
License-File: LICENCE
Classifier: Development Status :: 1 - Planning
Classifier: License :: OSI Approved :: GNU General Public License v3 or later (GPLv3+)
Classifier: Operating System :: OS Independent
Classifier: Programming Language :: Python :: 3
Requires-Python: >=3.7
